src/HC_SR04.py
test/__init__.py
test/test.py
test_kkimj/__init__.py
test_kkimj/test.py
test_kkimj-0.1.1.dist-info/LICENSE
test_kkimj-0.1.1.dist-info/METADATA
test_kkimj-0.1.1.dist-info/WHEEL
test_kkimj-0.1.1.dist-info/top_level.txt
test_kkimj-0.1.1.dist-info/RECORD
